jipy/__init__.py
jipy/main.py
jipy/multiprocessing_extras.py
jipy/quiz.py
jipy/utils.py
jipy/data/booleans.yml
jipy/data/dictionaries.yml
jipy/data/lists.yml
jipy/data/numbers.yml
jipy/data/sets.yml
jipy/data/strings.yml
jipy/data/tuples.yml
tests/__init__.py
tests/test_main.py
tests/test_quiz.py
tests/test_yaml.py
ji.py-0.0.1a9.dist-info/METADATA
ji.py-0.0.1a9.dist-info/WHEEL
ji.py-0.0.1a9.dist-info/entry_points.txt
ji.py-0.0.1a9.dist-info/top_level.txt
ji.py-0.0.1a9.dist-info/RECORD
