Metadata-Version: 2.1
Name: ji.py
Version: 0.0.1a9
Summary: 吉.py 是一個幫助學習Python的小工具
Home-page: https://github.com/amigcamel/ji.py
Author: amigcamel(阿吉/Aji)
Author-email: amigcamel@gmail.com
License: UNKNOWN
Platform: UNKNOWN
Requires-Dist: pyyaml (==3.13)
